spark_analyzer_mcp/.DS_Store
spark_analyzer_mcp/__init__.py
spark_analyzer_mcp/main.py
spark_analyzer_mcp/spark_analyzer.py
spark_analyzer_mcp/spark_log_parser.py
spark_analyzer_mcp-0.1.0.2.dist-info/WHEEL
spark_analyzer_mcp-0.1.0.2.dist-info/entry_points.txt
spark_analyzer_mcp-0.1.0.2.dist-info/METADATA
spark_analyzer_mcp-0.1.0.2.dist-info/RECORD
