Metadata-Version: 2.3
Name: spark-analyzer-mcp
Version: 0.1.0.2
Summary: Spark historical execution UI log analyzer exposed as an MCP server
Requires-Dist: fastapi>=0.104.0
Requires-Dist: uvicorn[standard]>=0.23.2
Requires-Dist: fastmcp>=0.1.0
Requires-Dist: python-dotenv>=1.0.0
Requires-Dist: loguru>=0.7.0
Requires-Dist: requests>=2.31.0
Requires-Dist: pydantic>=2.4.0
Requires-Python: >=3.13
